pymultigo/__init__.py
pymultigo/main.py
pymultigo-0.0.1.dist-info/METADATA
pymultigo-0.0.1.dist-info/WHEEL
pymultigo-0.0.1.dist-info/top_level.txt
pymultigo-0.0.1.dist-info/RECORD
