Metadata-Version: 2.1
Name: pymultigo
Version: 0.0.1
Summary: A MongoDB client to use multiple Mongo databases (MongoDB Atlas)
Home-page: https://github.com/JiangGua/pymultigo
Author: JiangGua
Author-email: pymultigo@mg.jonbgua.com
License: UNKNOWN
Platform: UNKNOWN
Classifier: Programming Language :: Python :: 3
Classifier: License :: OSI Approved :: MIT License
Classifier: Operating System :: OS Independent
Requires-Python: >=3.6
Requires-Dist: pymongo
